{
  "borderColor": "#5b5858",
  "backGroundColor": "#5b5858",
  "TextColor": "#FFFFFF",
  "NewUrl": "https://www.googleapis.com/blogger/v3/blogs/19925928/posts?fetchBodies=true&fetchImages=true&maxResults=15&orderBy=published&key=AIzaSyAfMgXuvr1PHhGTgmI9Y512d88rLO0k7xw",
  "CalendarUrl": "https://www.googleapis.com/calendar/v3/calendars/utn5eni303og5a1dkbbh3iso0o%40group.calendar.google.com/events?orderBy=startTime&singleEvents=true&timeMin={0}-{1}-{2}T00%3A00%3A00Z&fields=items&key=AIzaSyAfMgXuvr1PHhGTgmI9Y512d88rLO0k7xw", 
  "Catalogs":"http://catalog.cdpl.lib.in.us/polaris/Search/default.aspx?ctx=1.1033.0.0.1&type=Default",
  "Barcodetype": "CODABAR",
  "BarcodeStar": "A",
  "BarcodeEnd": "A",
  "LibName": "Crawfordsville District Public Library",
  "Items": [
    {
      "Id": 1,
      "branchName": "Crawfordsville District Public Library",
      "Latitude": "40.040128",
      "Longitude": "-86.901829",
      "phoneNumber": "765-362-2242",
      "Fax": "765-362-7986",
      "email": "ask@cdpl.lib.in.us",
      "LocationCode": "BU",
      "image": "CrawfordsvilleDistrictPublicLibrary.png",
      "Time": {
        "MondayOpen": "9:00 am",
        "MondayClose": "9:00 pm",
        "TuesdayOpen": "9:00 am",
        "TuesdayClose": "9:00 pm",
        "WednesdayOpen": "9:00 am",
        "WednesdayClose": "9:00 pm",
        "ThursdayOpen": "9:00 am", 
        ThursdayClose : "9:00 pm", 
        "FridayOpen": "9:00 am", 
        "FridayClose": "5:00 pm", 
        "SaturdayOpen": "9:00 am", 
        "SaturdayClose": "5:00 pm", 
        "SundayOpen": "1:00 pm", 
        "SundayClose": "5:00 pm",
      },
      "Address": {
        "Street": "205 S. Washington St.",
        "City": "Crawfordsville",
        "State": "IN",
        "Country": "United States",
        "zipCode": "47933",
      }
    },

  ]
}